README.rst
setup.cfg
setup.py
tests/__init__.py
tests/test_type.py
typedate/__init__.py
typedate/compat.py
typedate/utils.py
typedate.egg-info/PKG-INFO
typedate.egg-info/SOURCES.txt
typedate.egg-info/dependency_links.txt
typedate.egg-info/top_level.txt
typedate/type/__init__.py
typedate/type/date.py
typedate/type/delta.py
typedate/type/zone.py