Metadata-Version: 1.1
Name: typedate
Version: 1.1.0
Summary: Parsers related time for argparse
Home-page: https://github.com/righ/typedate
Author: righ
Author-email: righ.m9@gmail.com
License: Apache Software License 2.0
Keywords: argparse,date,datetime,timedelta,timezone
Platform: UNKNOWN
Classifier: Environment :: Console
Classifier: Intended Audience :: Developers
Classifier: License :: OSI Approved :: Apache Software License
Classifier: Programming Language :: Python
Classifier: Topic :: Software Development
